[
  {
    "name": "John Doe",
    "program": "SE 2k19",
    "comment": "\"Lorem ipsum dolor sit amet, consectetur adipisicing elit. Amet animi assumenda beatae, consectetur cumque.\""
  },
  {
    "name": "John Doe",
    "program": "SE 2k19",
    "comment": "\"Lorem ipsum dolor sit amet, consectetur adipisicing elit. Amet animi assumenda beatae, consectetur cumque.\""
  },
  {
    "name": "John Doe",
    "program": "SE 2k19",
    "comment": "\"Lorem ipsum dolor sit amet, consectetur adipisicing elit. Amet animi assumenda beatae, consectetur cumque.\""
  },
  {
    "name": "John Doe",
    "program": "SE 2k19",
    "comment": "\"Lorem ipsum dolor sit amet, consectetur adipisicing elit. Amet animi assumenda beatae, consectetur cumque.\""
  },
  {
    "name": "John Doe",
    "program": "SE 2k19",
    "comment": "\"Lorem ipsum dolor sit amet, consectetur adipisicing elit. Amet animi assumenda beatae, consectetur cumque.\""
  },
  {
    "name": "John Doe",
    "program": "SE 2k19",
    "comment": "\"Lorem ipsum dolor sit amet, consectetur adipisicing elit. Amet animi assumenda beatae, consectetur cumque.\""
  },
  {
    "name": "John Doe",
    "program": "SE 2k19",
    "comment": "\"Lorem ipsum dolor sit amet, consectetur adipisicing elit. Amet animi assumenda beatae, consectetur cumque.\""
  },
  {
    "name": "John Doe",
    "program": "SE 2k19",
    "comment": "\"Lorem ipsum dolor sit amet, consectetur adipisicing elit. Amet animi assumenda beatae, consectetur cumque.\""
  },
  {
    "name": "John Doe",
    "program": "SE 2k19",
    "comment": "\"Lorem ipsum dolor sit amet, consectetur adipisicing elit. Amet animi assumenda beatae, consectetur cumque.\""
  }
]